pycatima/__init__.py
pycatima/_ext.cp311-win_amd64.pyd
pycatima-1.98.dist-info/METADATA
pycatima-1.98.dist-info/WHEEL
pycatima-1.98.dist-info/RECORD
