Metadata-Version: 2.1
Name: pycatima
Version: 1.98
Summary: Python interface to CATIMA library
Author-Email: Andrej Prochazka <hrocho@vodacionline.sk>
Maintainer-Email: Angus Hollands <goosey15@gmail.com>
Requires-Python: >=3.8
Provides-Extra: test
Requires-Dist: pytest; extra == "test"
